[
    {
        "id":1,
        "img":"https://images.pexels.com/photos/771742/pexels-photo-771742.jpeg?auto=compress&cs=tinysrgb&dpr=1&w=500",
        "name":"Steve",
        "position":"CEO",
        "description":"Lorem ipsum dolor sit amet consectetur adipisicing elit."
    },
    {
        "id":2,
        "img":"https://images.pexels.com/photos/771742/pexels-photo-771742.jpeg?auto=compress&cs=tinysrgb&dpr=1&w=500",
        "name":"Hugoes",
        "position":"CTO",
        "description":"Lorem ipsum dolor sit amet consectetur adipisicing elit."
    },
    {
        "id":3,
        "img":"https://images.pexels.com/photos/771742/pexels-photo-771742.jpeg?auto=compress&cs=tinysrgb&dpr=1&w=500",
        "name":"James",
        "position":"Engineer",
        "description":"Lorem ipsum dolor sit amet consectetur adipisicing elit."
    },
    {
        "id":4,
        "img":"https://images.pexels.com/photos/771742/pexels-photo-771742.jpeg?auto=compress&cs=tinysrgb&dpr=1&w=500",
        "name":"Kline",
        "position":"Designer",
        "description":"Lorem ipsum dolor sit amet consectetur adipisicing elit."
    },
    {
        "id":5,
        "img":"https://images.pexels.com/photos/771742/pexels-photo-771742.jpeg?auto=compress&cs=tinysrgb&dpr=1&w=500",
        "name":"Loara",
        "position":"Chief Executive",
        "description":"Lorem ipsum dolor sit amet consectetur adipisicing elit."
    }
]